{
    "data": [
        {
            "game_state": {
                "white_king_in_check": false,
                "black_king_in_check": false,
                "is_game_terminated": false,
                "is_game_drawn": false,
                "moves_for_f_rule": 1,
                "fen": "r4b1r/3kp2p/4bp1n/p1p2P2/1q1nP1Pp/pPQ5/B1PNN3/R1B1K2R w KQ - 1 29"
            },
            "moves": {
                "1": [
                    "Pg6"
                ],
                "2": [
                    "Pd4",
                    "Pc5"
                ],
                "3": [
                    "Nd2",
                    "Bg7"
                ],
                "4": [
                    "Pf4",
                    "Pb5"
                ],
                "5": [
                    "Nh3",
                    "Pa5"
                ],
                "6": [
                    "Pa4",
                    "Pd6"
                ],
                "7": [
                    "Pe4",
                    "Qc7"
                ],
                "8": [
                    "Pg3",
                    "Qb7"
                ],
                "9": [
                    "Rg1",
                    "Pf6"
                ],
                "10": [
                    "dxc5",
                    "Nh6"
                ],
                "11": [
                    "Rh1",
                    "Pg5"
                ],
                "12": [
                    "Pf5",
                    "Be6"
                ],
                "13": [
                    "Ng1",
                    "dxc5"
                ],
                "14": [
                    "Ra3",
                    "Qa6"
                ],
                "15": [
                    "Bd3",
                    "Nf7"
                ],
                "16": [
                    "Qe2",
                    "bxa4"
                ],
                "17": [
                    "Pg4",
                    "Nh6"
                ],
                "18": [
                    "Nb1",
                    "Bf8"
                ],
                "19": [
                    "Ra1",
                    "Nc6"
                ],
                "20": [
                    "Nd2",
                    "Nd4"
                ],
                "21": [
                    "Bc4",
                    "gxh4"
                ],
                "22": [
                    "Ba2",
                    "Pa3"
                ],
                "23": [
                    "Qe3",
                    "Qb6"
                ],
                "24": [
                    "Qg3",
                    "Qb4"
                ],
                "25": [
                    "Qb3",
                    "Kd8"
                ],
                "26": [
                    "Ne2",
                    "Qb8"
                ],
                "27": [
                    "Qc3",
                    "Qb4"
                ],
                "28": [
                    "Pb3",
                    "Kd7"
                ]
            },
            "error": "Invalid move at _move_piece.1",
            "game_values": {
                "white": 0,
                "black": 0
            },
            "player_turn": "white",
            "wlm": [
                "Rb1",
                "Rh2",
                "Rh3",
                "Rg1",
                "Rf1",
                "Nf3",
                "Nc4",
                "Nb1",
                "Nf1",
                "Ng3",
                "Nf4",
                "Ng1",
                "Bb2",
                "Bb1",
                "Qb2",
                "Qc4",
                "Qd3",
                "Qe3",
                "Qf3",
                "Qg3",
                "Qh3",
                "Kf2",
                "Kd1",
                "Kf1",
                "Pe5",
                "fxe6",
                "Pg5"
            ],
            "blm": [
                "Pa4",
                "Pc4",
                "Ph3",
                "Ra7",
                "Ra6",
                "Rb8",
                "Rc8",
                "Rd8",
                "Re8",
                "Rg8",
                "Nc6",
                "Nb5",
                "Nf3",
                "Ng8",
                "Nf7",
                "Bd5",
                "Bc4",
                "Bf7",
                "Bg8",
                "Bg7",
                "Qb5",
                "Qb6",
                "Qb7",
                "Qb8",
                "Qa4",
                "Qc4",
                "Ke8",
                "Kd8",
                "Kc8",
                "Kc7",
                "Kc6",
                "Kd6"
            ]
        }
    ]
}